nodeeditor/__init__.py
nodeeditor/node_content_widget.py
nodeeditor/node_edge.py
nodeeditor/node_edge_dragging.py
nodeeditor/node_edge_intersect.py
nodeeditor/node_edge_rerouting.py
nodeeditor/node_edge_snapping.py
nodeeditor/node_edge_validators.py
nodeeditor/node_editor_widget.py
nodeeditor/node_editor_window.py
nodeeditor/node_graphics_cutline.py
nodeeditor/node_graphics_edge.py
nodeeditor/node_graphics_edge_path.py
nodeeditor/node_graphics_node.py
nodeeditor/node_graphics_scene.py
nodeeditor/node_graphics_socket.py
nodeeditor/node_graphics_view.py
nodeeditor/node_node.py
nodeeditor/node_scene.py
nodeeditor/node_scene_clipboard.py
nodeeditor/node_scene_history.py
nodeeditor/node_serializable.py
nodeeditor/node_socket.py
nodeeditor/utils.py
nodeeditor/utils_no_qt.py
nodeeditor/qss/nodestyle.qss
nodeeditor-0.9.14.dist-info/LICENCE
nodeeditor-0.9.14.dist-info/METADATA
nodeeditor-0.9.14.dist-info/WHEEL
nodeeditor-0.9.14.dist-info/top_level.txt
nodeeditor-0.9.14.dist-info/RECORD
