Metadata-Version: 2.1
Name: nodeeditor
Version: 0.9.14
Summary: Python Node Editor using PyQt5
Home-page: https://gitlab.com/pavel.krupala/pyqt-node-editor.git
Author: Pavel Křupala
Author-email: pavel.krupala@gmail.com
License: MIT license
Keywords: nodeeditor
Classifier: Development Status :: 3 - Alpha
Classifier: Intended Audience :: Developers
Classifier: License :: OSI Approved :: MIT License
Classifier: Natural Language :: English
Classifier: Programming Language :: Python :: 3
Classifier: Programming Language :: Python :: 3.5
Classifier: Programming Language :: Python :: 3.6
Classifier: Programming Language :: Python :: 3.7
Classifier: Programming Language :: Python :: 3.8
License-File: LICENCE
Requires-Dist: QtPy >=1.9.0
